Cyda/__init__.py
Cyda/main.py
cyda-1.5.7.2.dist-info/METADATA
cyda-1.5.7.2.dist-info/WHEEL
cyda-1.5.7.2.dist-info/entry_points.txt
cyda-1.5.7.2.dist-info/top_level.txt
cyda-1.5.7.2.dist-info/RECORD
