Metadata-Version: 2.4
Name: Cyda
Version: 1.5.7.2
Dynamic: description
Dynamic: description-content-type
